{
    "tables": {
        "Customers": {
            "tableName": "Customers",
            "schema": {
                "id": {
                    "allowNull": false,
                    "primaryKey": true,
                    "autoIncrement": true,
                    "field": "id",
                    "seqType": "Sequelize.INTEGER"
                },
                "isConfirmed": {
                    "allowNull": false,
                    "defaultValue": {
                        "value": false
                    },
                    "field": "isConfirmed",
                    "seqType": "Sequelize.BOOLEAN"
                },
                "name": {
                    "allowNull": false,
                    "field": "name",
                    "seqType": "Sequelize.STRING"
                },
                "email": {
                    "allowNull": false,
                    "unique": true,
                    "validate": {
                        "is": {}
                    },
                    "field": "email",
                    "seqType": "Sequelize.STRING"
                },
                "passwordHash": {
                    "allowNull": false,
                    "field": "passwordHash",
                    "seqType": "Sequelize.STRING"
                },
                "address": {
                    "allowNull": false,
                    "field": "address",
                    "seqType": "Sequelize.STRING"
                },
                "phoneNumber": {
                    "allowNull": false,
                    "field": "phoneNumber",
                    "seqType": "Sequelize.STRING"
                },
                "createdAt": {
                    "allowNull": false,
                    "field": "createdAt",
                    "seqType": "Sequelize.DATE"
                },
                "updatedAt": {
                    "allowNull": false,
                    "field": "updatedAt",
                    "seqType": "Sequelize.DATE"
                }
            },
            "indexes": []
        },
        "Merchants": {
            "tableName": "Merchants",
            "schema": {
                "id": {
                    "allowNull": false,
                    "primaryKey": true,
                    "autoIncrement": true,
                    "field": "id",
                    "seqType": "Sequelize.INTEGER"
                },
                "isConfirmed": {
                    "allowNull": false,
                    "defaultValue": {
                        "value": false
                    },
                    "field": "isConfirmed",
                    "seqType": "Sequelize.BOOLEAN"
                },
                "type": {
                    "allowNull": false,
                    "field": "type",
                    "seqType": "Sequelize.STRING"
                },
                "name": {
                    "allowNull": false,
                    "field": "name",
                    "seqType": "Sequelize.STRING"
                },
                "email": {
                    "allowNull": false,
                    "unique": true,
                    "validate": {
                        "is": {}
                    },
                    "field": "email",
                    "seqType": "Sequelize.STRING"
                },
                "passwordHash": {
                    "allowNull": false,
                    "field": "passwordHash",
                    "seqType": "Sequelize.STRING"
                },
                "address": {
                    "allowNull": false,
                    "field": "address",
                    "seqType": "Sequelize.STRING"
                },
                "phoneNumber": {
                    "allowNull": false,
                    "field": "phoneNumber",
                    "seqType": "Sequelize.STRING"
                },
                "createdAt": {
                    "allowNull": false,
                    "field": "createdAt",
                    "seqType": "Sequelize.DATE"
                },
                "updatedAt": {
                    "allowNull": false,
                    "field": "updatedAt",
                    "seqType": "Sequelize.DATE"
                }
            },
            "indexes": []
        },
        "Orders": {
            "tableName": "Orders",
            "schema": {
                "id": {
                    "allowNull": false,
                    "primaryKey": true,
                    "autoIncrement": true,
                    "field": "id",
                    "seqType": "Sequelize.INTEGER"
                },
                "isPaid": {
                    "allowNull": false,
                    "defaultValue": {
                        "value": false
                    },
                    "field": "isPaid",
                    "seqType": "Sequelize.BOOLEAN"
                },
                "deliveryAddress": {
                    "allowNull": false,
                    "field": "deliveryAddress",
                    "seqType": "Sequelize.STRING"
                },
                "status": {
                    "allowNull": false,
                    "field": "status",
                    "seqType": "Sequelize.STRING"
                },
                "createdAt": {
                    "allowNull": false,
                    "field": "createdAt",
                    "seqType": "Sequelize.DATE"
                },
                "updatedAt": {
                    "allowNull": false,
                    "field": "updatedAt",
                    "seqType": "Sequelize.DATE"
                },
                "CustomerId": {
                    "allowNull": true,
                    "references": {
                        "model": "Customers",
                        "key": "id"
                    },
                    "onDelete": "SET NULL",
                    "onUpdate": "CASCADE",
                    "field": "CustomerId",
                    "seqType": "Sequelize.INTEGER"
                },
                "MerchantId": {
                    "allowNull": true,
                    "references": {
                        "model": "Merchants",
                        "key": "id"
                    },
                    "onDelete": "SET NULL",
                    "onUpdate": "CASCADE",
                    "field": "MerchantId",
                    "seqType": "Sequelize.INTEGER"
                }
            },
            "indexes": []
        },
        "OrderDetails": {
            "tableName": "OrderDetails",
            "schema": {
                "id": {
                    "allowNull": false,
                    "primaryKey": true,
                    "autoIncrement": true,
                    "field": "id",
                    "seqType": "Sequelize.INTEGER"
                },
                "productPrice": {
                    "allowNull": false,
                    "field": "productPrice",
                    "seqType": "Sequelize.DECIMAL"
                },
                "productQuantity": {
                    "allowNull": false,
                    "field": "productQuantity",
                    "seqType": "Sequelize.INTEGER"
                },
                "createdAt": {
                    "allowNull": false,
                    "field": "createdAt",
                    "seqType": "Sequelize.DATE"
                },
                "updatedAt": {
                    "allowNull": false,
                    "field": "updatedAt",
                    "seqType": "Sequelize.DATE"
                },
                "OrderId": {
                    "allowNull": true,
                    "references": {
                        "model": "Orders",
                        "key": "id"
                    },
                    "onDelete": "CASCADE",
                    "onUpdate": "CASCADE",
                    "field": "OrderId",
                    "seqType": "Sequelize.INTEGER"
                },
                "ProductId": {
                    "allowNull": true,
                    "references": {
                        "model": "Products",
                        "key": "id"
                    },
                    "onDelete": "SET NULL",
                    "onUpdate": "CASCADE",
                    "field": "ProductId",
                    "seqType": "Sequelize.INTEGER"
                }
            },
            "indexes": []
        },
        "Products": {
            "tableName": "Products",
            "schema": {
                "id": {
                    "allowNull": false,
                    "primaryKey": true,
                    "autoIncrement": true,
                    "field": "id",
                    "seqType": "Sequelize.INTEGER"
                },
                "isInView": {
                    "allowNull": false,
                    "defaultValue": {
                        "value": true
                    },
                    "field": "isInView",
                    "seqType": "Sequelize.BOOLEAN"
                },
                "name": {
                    "allowNull": false,
                    "field": "name",
                    "seqType": "Sequelize.STRING"
                },
                "description": {
                    "allowNull": false,
                    "field": "description",
                    "seqType": "Sequelize.STRING"
                },
                "price": {
                    "allowNull": false,
                    "field": "price",
                    "seqType": "Sequelize.DECIMAL"
                },
                "quantity": {
                    "allowNull": false,
                    "field": "quantity",
                    "seqType": "Sequelize.INTEGER"
                },
                "imageUrl": {
                    "allowNull": false,
                    "field": "imageUrl",
                    "seqType": "Sequelize.STRING"
                },
                "createdAt": {
                    "allowNull": false,
                    "field": "createdAt",
                    "seqType": "Sequelize.DATE"
                },
                "updatedAt": {
                    "allowNull": false,
                    "field": "updatedAt",
                    "seqType": "Sequelize.DATE"
                },
                "MerchantId": {
                    "allowNull": true,
                    "references": {
                        "model": "Merchants",
                        "key": "id"
                    },
                    "onDelete": "SET NULL",
                    "onUpdate": "CASCADE",
                    "field": "MerchantId",
                    "seqType": "Sequelize.INTEGER"
                },
                "CategoryId": {
                    "allowNull": true,
                    "references": {
                        "model": "Categories",
                        "key": "id"
                    },
                    "onDelete": "SET NULL",
                    "onUpdate": "CASCADE",
                    "field": "CategoryId",
                    "seqType": "Sequelize.INTEGER"
                }
            },
            "indexes": []
        },
        "Categories": {
            "tableName": "Categories",
            "schema": {
                "id": {
                    "allowNull": false,
                    "primaryKey": true,
                    "autoIncrement": true,
                    "field": "id",
                    "seqType": "Sequelize.INTEGER"
                },
                "name": {
                    "allowNull": false,
                    "field": "name",
                    "seqType": "Sequelize.STRING"
                },
                "createdAt": {
                    "allowNull": false,
                    "field": "createdAt",
                    "seqType": "Sequelize.DATE"
                },
                "updatedAt": {
                    "allowNull": false,
                    "field": "updatedAt",
                    "seqType": "Sequelize.DATE"
                }
            },
            "indexes": []
        }
    },
    "revision": 1
}